README.txt
setup.py
relayserver/__init__.py
relayserver/base_protocol.py
relayserver/config.py
relayserver/endpoint.py
relayserver/main.py
relayserver/read_buffer.py
relayserver/utility.py
relayserver.egg-info/PKG-INFO
relayserver.egg-info/SOURCES.txt
relayserver.egg-info/dependency_links.txt
relayserver.egg-info/entry_points.txt
relayserver.egg-info/not-zip-safe
relayserver.egg-info/requires.txt
relayserver.egg-info/top_level.txt
relayserver/boot/__init__.py
relayserver/boot/host_process.py
relayserver/boot/relay.py
relayserver/message_types/__init__.py
relayserver/message_types/command_pb2.py
relayserver/message_types/hello_pb2.py
relayserver/real/__init__.py
relayserver/real/echo_server.py
relayserver/real/ireal_server.py