Metadata-Version: 1.0
Name: relayserver
Version: 1.1.1
Summary: A relay-server to defeat NATs, with pools.
Home-page: https://github.com/dsoprea/RelayServer
Author: Dustin Oprea
Author-email: myselfasunder@gmail.com
License: LGPL
Keywords: relay-server nat network client server
Platform: UNKNOWN
